{"0": {"x": 760, "y": 40, "width": 400, "height": 57.1875, "href": "https://frouy.weebly.com/", "url": "https://frouy.weebly.com/", "quality_check": ["complete", "in-complete", "complete"]}, "1": {"x": 785.890625, "y": 141.1875, "width": 348.203125, "height": 29, "href": "https://frouy.weebly.com/", "url": "https://frouy.weebly.com/", "quality_check": ["complete or in-complete", "complete"]}, "2": {"x": 923.0625, "y": 764.921875, "width": 516.9375, "height": 17, "href": "", "url": "https://frouy.weebly.com/", "quality_check": ["complete or in-complete", "complete or in-complete", "complete"]}, "3": {"x": 884.53125, "y": 1134.71875, "width": 150.9375, "height": 48.296875, "href": "https://waufooke.com/4/5658924", "url": "https://frouy.weebly.com/", "quality_check": ["complete or in-complete", "complete or in-complete", "complete"]}, "4": {"x": 480, "y": 1333.609375, "width": 160, "height": 35, "href": null, "url": "https://frouy.weebly.com/", "quality_check": ["complete", "complete"]}, "5": {"x": 660, "y": 1333.609375, "width": 220, "height": 35, "href": null, "url": "https://frouy.weebly.com/", "quality_check": ["complete"]}, "6": {"x": 480, "y": 1416.609375, "width": 370, "height": 35, "href": null, "url": "https://frouy.weebly.com/", "quality_check": ["complete", "complete"]}, "7": {"x": 480, "y": 1494.609375, "width": 370, "height": 35, "href": null, "url": "error: Page.goto: net::ERR_ABORTED; maybe frame was detached?\nCall log:\n  - navigating to \"https://frouy.weebly.com/\", waiting until \"load\"\n"}, "8": {"x": 480, "y": 1572.609375, "width": 370, "height": 35, "href": null, "url": "https://frouy.weebly.com/", "quality_check": ["complete"]}, "10": {"x": 895.21875, "y": 1617.609375, "width": 129.5625, "height": 41, "href": "", "url": "https://frouy.weebly.com/", "quality_check": ["complete"]}, "11": {"x": 485, "y": 1664.71875, "width": 309.484375, "height": 309.484375, "href": null, "url": "https://frouy.weebly.com/", "quality_check": ["complete", "in-complete", "complete or in-complete", "complete"]}, "12": {"x": 804.484375, "y": 1664.71875, "width": 309.484375, "height": 309.484375, "href": null, "url": "https://frouy.weebly.com/", "quality_check": ["complete"]}, "13": {"x": 1123.96875, "y": 1664.71875, "width": 309.484375, "height": 309.484375, "href": null, "url": "https://frouy.weebly.com/", "quality_check": ["complete"]}, "14": {"x": 485, "y": 1906.828125, "width": 309.484375, "height": 309.484375, "href": null, "url": "https://frouy.weebly.com/", "quality_check": ["complete"]}, "15": {"x": 804.484375, "y": 1906.828125, "width": 309.484375, "height": 309.484375, "href": null, "url": "error: Page.goto: Target page, context or browser has been closed\nCall log:\n  - navigating to \"https://frouy.weebly.com/\", waiting until \"load\"\n"}, "16": {"x": 1123.96875, "y": 1906.828125, "width": 309.484375, "height": 309.484375, "href": null, "url": "https://frouy.weebly.com/", "quality_check": ["complete", "in-complete", "complete or in-complete", "complete or in-complete", "complete"]}, "17": {"x": 485, "y": 2148.9375, "width": 309.484375, "height": 309.484375, "href": null, "url": "https://frouy.weebly.com/", "quality_check": ["complete"]}, "18": {"x": 804.484375, "y": 2148.9375, "width": 309.484375, "height": 309.484375, "href": null, "url": "https://frouy.weebly.com/", "quality_check": ["complete or in-complete", "complete or in-complete", "complete or in-complete", "complete"]}, "19": {"x": 1123.96875, "y": 2148.9375, "width": 309.484375, "height": 309.484375, "href": null, "url": "https://frouy.weebly.com/", "quality_check": ["complete or in-complete", "complete or in-complete", "complete"]}, "20": {"x": 485, "y": 2391.046875, "width": 309.484375, "height": 309.484375, "href": null, "url": "https://frouy.weebly.com/", "quality_check": ["complete"]}, "21": {"x": 804.484375, "y": 2391.046875, "width": 309.484375, "height": 309.484375, "href": null, "url": "https://frouy.weebly.com/", "quality_check": ["complete"]}, "22": {"x": 1123.96875, "y": 2391.046875, "width": 309.484375, "height": 309.484375, "href": null, "url": "https://frouy.weebly.com/", "quality_check": ["complete or in-complete", "complete or in-complete", "complete"]}, "23": {"x": 485, "y": 2633.15625, "width": 309.484375, "height": 309.484375, "href": null, "url": "https://frouy.weebly.com/", "quality_check": ["complete or in-complete", "complete or in-complete", "complete or in-complete", "complete", "complete"]}, "24": {"x": 804.484375, "y": 2633.15625, "width": 309.484375, "height": 309.484375, "href": null, "url": "https://frouy.weebly.com/", "quality_check": ["complete or in-complete", "complete or in-complete", "complete"]}, "25": {"x": 1123.96875, "y": 2633.15625, "width": 309.484375, "height": 309.484375, "href": null, "url": "https://frouy.weebly.com/", "quality_check": ["complete or in-complete", "complete"]}, "26": {"x": 485, "y": 2875.265625, "width": 309.484375, "height": 309.484375, "href": null, "url": "error: Page.goto: Target page, context or browser has been closed\nCall log:\n  - navigating to \"https://frouy.weebly.com/\", waiting until \"load\"\n"}, "27": {"x": 804.484375, "y": 2875.265625, "width": 309.484375, "height": 309.484375, "href": null, "url": "https://frouy.weebly.com/", "quality_check": ["complete", "complete or in-complete", "complete or in-complete", "complete"]}, "28": {"x": 1123.96875, "y": 2875.265625, "width": 309.484375, "height": 309.484375, "href": null, "url": "https://frouy.weebly.com/", "quality_check": ["complete"]}, "29": {"x": 485, "y": 3117.375, "width": 309.484375, "height": 309.484375, "href": null, "url": "https://frouy.weebly.com/", "quality_check": ["complete"]}, "30": {"x": 804.484375, "y": 3117.375, "width": 309.484375, "height": 309.484375, "href": null, "url": "https://frouy.weebly.com/", "quality_check": ["complete"]}, "31": {"x": 1123.96875, "y": 3117.375, "width": 309.484375, "height": 309.484375, "href": null, "url": "https://frouy.weebly.com/", "quality_check": ["complete", "complete"]}, "32": {"x": 485, "y": 3359.484375, "width": 309.484375, "height": 309.484375, "href": null, "url": "https://frouy.weebly.com/", "quality_check": ["complete or in-complete", "complete or in-complete", "complete or in-complete", "complete or in-complete", "complete or in-complete", "complete"]}, "33": {"x": 804.484375, "y": 3359.484375, "width": 309.484375, "height": 309.484375, "href": null, "url": "https://frouy.weebly.com/", "quality_check": ["complete", "in-complete", "complete"]}, "34": {"x": 1123.96875, "y": 3359.484375, "width": 309.484375, "height": 309.484375, "href": null, "url": "https://frouy.weebly.com/", "quality_check": ["complete or in-complete", "complete or in-complete", "complete"]}, "35": {"x": 485, "y": 3601.59375, "width": 309.484375, "height": 309.484375, "href": null, "url": "https://frouy.weebly.com/", "quality_check": ["complete or in-complete", "complete or in-complete", "complete"]}, "36": {"x": 804.484375, "y": 3601.59375, "width": 309.484375, "height": 309.484375, "href": null, "url": "https://frouy.weebly.com/", "quality_check": ["complete", "complete or in-complete", "complete"]}, "37": {"x": 1123.96875, "y": 3601.59375, "width": 309.484375, "height": 309.484375, "href": null, "url": "https://frouy.weebly.com/", "quality_check": ["complete"]}, "38": {"x": 485, "y": 3843.703125, "width": 309.484375, "height": 309.484375, "href": null, "url": "https://frouy.weebly.com/", "quality_check": ["complete or in-complete", "complete or in-complete", "complete"]}, "39": {"x": 804.484375, "y": 3843.703125, "width": 309.484375, "height": 309.484375, "href": null, "url": "https://frouy.weebly.com/", "quality_check": ["complete or in-complete", "complete or in-complete", "complete"]}, "40": {"x": 1123.96875, "y": 3843.703125, "width": 309.484375, "height": 309.484375, "href": null, "url": "https://frouy.weebly.com/", "quality_check": ["complete"]}, "41": {"x": 485, "y": 4085.8125, "width": 309.484375, "height": 309.484375, "href": null, "url": "https://frouy.weebly.com/", "quality_check": ["complete or in-complete", "complete"]}, "42": {"x": 804.484375, "y": 4085.8125, "width": 309.484375, "height": 309.484375, "href": null, "url": "https://frouy.weebly.com/", "quality_check": ["complete or in-complete", "complete", "complete"]}, "43": {"x": 1123.96875, "y": 4085.8125, "width": 309.484375, "height": 309.484375, "href": null, "url": "https://frouy.weebly.com/", "quality_check": ["complete", "in-complete", "complete"]}, "44": {"x": 485, "y": 4327.921875, "width": 309.484375, "height": 309.484375, "href": null, "url": "https://frouy.weebly.com/", "quality_check": ["complete or in-complete", "complete or in-complete", "complete or in-complete", "complete or in-complete", "complete"]}, "45": {"x": 804.484375, "y": 4327.921875, "width": 309.484375, "height": 309.484375, "href": null, "url": "https://frouy.weebly.com/", "quality_check": ["complete or in-complete", "complete or in-complete", "complete"]}, "46": {"x": 1123.96875, "y": 4327.921875, "width": 309.484375, "height": 309.484375, "href": null, "url": "https://frouy.weebly.com/", "quality_check": ["complete"]}, "47": {"x": 485, "y": 4570.03125, "width": 309.484375, "height": 309.484375, "href": null, "url": "https://frouy.weebly.com/", "quality_check": ["complete"]}, "48": {"x": 804.484375, "y": 4570.03125, "width": 309.484375, "height": 309.484375, "href": null, "url": "https://frouy.weebly.com/", "quality_check": ["complete"]}, "49": {"x": 1123.96875, "y": 4570.03125, "width": 309.484375, "height": 309.484375, "href": null, "url": "error: Page.goto: Target page, context or browser has been closed\nCall log:\n  - navigating to \"https://frouy.weebly.com/\", waiting until \"load\"\n"}, "50": {"x": 485, "y": 4812.140625, "width": 309.484375, "height": 309.484375, "href": null, "url": "https://frouy.weebly.com/", "quality_check": ["complete or in-complete", "complete"]}, "51": {"x": 804.484375, "y": 4812.140625, "width": 309.484375, "height": 309.484375, "href": null, "url": "https://frouy.weebly.com/", "quality_check": ["complete"]}, "52": {"x": 1123.96875, "y": 4812.140625, "width": 309.484375, "height": 309.484375, "href": null, "url": "https://frouy.weebly.com/", "quality_check": ["complete or in-complete", "complete or in-complete", "complete or in-complete", "complete or in-complete", "complete"]}, "53": {"x": 485, "y": 5054.25, "width": 309.484375, "height": 309.484375, "href": null, "url": "https://frouy.weebly.com/", "quality_check": ["complete"]}, "54": {"x": 804.484375, "y": 5054.25, "width": 309.484375, "height": 309.484375, "href": null, "url": "https://frouy.weebly.com/", "quality_check": ["complete or in-complete", "complete or in-complete", "complete"]}, "55": {"x": 1123.96875, "y": 5054.25, "width": 309.484375, "height": 309.484375, "href": null, "url": "https://frouy.weebly.com/", "quality_check": ["complete or in-complete", "complete", "complete"]}, "56": {"x": 485, "y": 5296.359375, "width": 309.484375, "height": 309.484375, "href": null, "url": "https://frouy.weebly.com/", "quality_check": ["complete"]}, "57": {"x": 804.484375, "y": 5296.359375, "width": 309.484375, "height": 309.484375, "href": null, "url": "https://frouy.weebly.com/", "quality_check": ["complete", "complete"]}, "58": {"x": 10, "y": 1018, "width": 290, "height": 62, "href": "https://www.weebly.com/signup?utm_source=internal&utm_medium=footer", "url": "https://frouy.weebly.com/", "quality_check": ["complete or in-complete", "complete or in-complete", "complete or in-complete", "complete"]}, "59": {"x": 15.796875, "y": 1018, "width": 284.203125, "height": 77, "href": null, "url": "https://frouy.weebly.com/", "quality_check": ["complete", "complete"]}, "63": {"x": 55.796875, "y": 1198.28125, "width": 200, "height": 36, "href": null, "url": "https://frouy.weebly.com/", "quality_check": ["complete", "complete"]}, "60": {"x": 15.796875, "y": 1033, "width": 280, "height": 277.28125, "href": null, "url": "https://frouy.weebly.com/", "quality_check": ["complete", "complete or in-complete", "complete"]}, "base": "https://frouy.weebly.com/"}