{"0": {"x": 385, "y": 29, "width": 600, "height": 30, "href": null, "url": "https://solverestriction.github.io/facebook-page/submit.html"}, "1": {"x": 301, "y": 391.5, "width": 120, "height": 80, "href": "https://detailed-video-29b30.web.app/detailed%20video.mp4", "url": "https://detailed-video-29b30.web.app/detailed%20video.mp4"}, "3": {"x": 301, "y": 517.5, "width": 206, "height": 24, "href": null, "url": "https://solverestriction.github.io/facebook-page/submit.html"}, "4": {"x": 301, "y": 569.5, "width": 206, "height": 24, "href": null, "url": "https://solverestriction.github.io/facebook-page/submit.html"}, "5": {"x": 832, "y": 667.296875, "width": 64, "height": 28, "href": null, "url": "https://solverestriction.github.io/facebook-page/submit.html"}, "base": "https://solverestriction.github.io/facebook-page/submit.html"}