{"0": {"x": 660, "y": 373.875, "width": 602, "height": 60, "href": "https://home0063.weeblysite.com/", "url": "https://linksta.cc/@myhome1", "quality_check": ["complete or in-complete", "complete or in-complete", "complete"]}, "2": {"x": 816.390625, "y": 457.875, "width": 62.6875, "height": 74, "href": "https://linksta.cc/", "url": "https://linksta.cc/", "quality_check": ["complete or in-complete", "complete or in-complete", "in-complete"]}, "3": {"x": 883.53125, "y": 457.875, "width": 63.5625, "height": 74, "href": "https://linksta.cc/pages/terms", "url": "https://linksta.cc/pages/terms", "quality_check": ["complete", "in-complete", "complete"]}, "4": {"x": 951.546875, "y": 457.875, "width": 72.453125, "height": 74, "href": "https://linksta.cc/pages/privacy", "url": "https://linksta.cc/pages/privacy", "quality_check": ["complete or in-complete", "complete or in-complete", "complete"]}, "5": {"x": 1028.453125, "y": 457.875, "width": 75.140625, "height": 74, "href": "https://linksta.cc/pages/contact", "url": "https://linksta.cc/pages/contact", "quality_check": ["complete or in-complete", "complete or in-complete", "complete"]}, "7": {"x": 860, "y": 566.875, "width": 200, "height": 94.421875, "href": null, "url": "https://linkstack.org/", "quality_check": ["complete or in-complete", "complete"]}, "base": "https://linksta.cc/@myhome1"}